bt_staking_explorer-1.1.1.dist-info/METADATA
bt_staking_explorer-1.1.1.dist-info/WHEEL
bt_staking_explorer/__init__.py
bt_staking_explorer/__init__.pyi
bt_staking_explorer/bt_staking_explorer.cpython-311-x86_64-linux-gnu.so
bt_staking_explorer/client/__init__.py
bt_staking_explorer/client/staking_client.py
bt_staking_explorer/types/__init__.py
bt_staking_explorer-1.1.1.dist-info/RECORD
