Metadata-Version: 2.4
Name: bt-staking-explorer
Version: 1.1.1
Classifier: Programming Language :: Rust
Classifier: Programming Language :: Python :: Implementation :: CPython
Classifier: Programming Language :: Python :: Implementation :: PyPy
Requires-Dist: substrate-interface>=1.7.0
Requires-Python: >=3.9
